cookiecutter_poetry/__init__.py
cookiecutter_poetry/foo.py
cookiecutter_poetry_deepak-0.0.2.dist-info/LICENSE
cookiecutter_poetry_deepak-0.0.2.dist-info/METADATA
cookiecutter_poetry_deepak-0.0.2.dist-info/WHEEL
cookiecutter_poetry_deepak-0.0.2.dist-info/RECORD
