Metadata-Version: 2.1
Name: cookiecutter_poetry_deepak
Version: 0.0.2
Summary: A Demo Project for Cookiecutter Poetry
Home-page: https://github.com/DeepakPant93/cookiecutter-poetry
Author: Deepak Pant
Author-email: deepak.93p@gmail.com
Requires-Python: >=3.8,<4.0
Classifier: Programming Language :: Python :: 3
Classifier: Programming Language :: Python :: 3.8
Classifier: Programming Language :: Python :: 3.9
Classifier: Programming Language :: Python :: 3.10
Classifier: Programming Language :: Python :: 3.11
Classifier: Programming Language :: Python :: 3.12
Project-URL: Documentation, https://DeepakPant93.github.io/cookiecutter-poetry/
Project-URL: Repository, https://github.com/DeepakPant93/cookiecutter-poetry
